{
  "login": {
    "email": "sun@test.com",
    "password": "123445"
  },
  "stations": [
    {
      "name": "다음페이지?",
      "id": 8
    },
    {
      "name": "성신여대입구역",
      "id": 9
    },
    {
      "name": "와아앙",
      "id": 10
    },
    {
      "name": "밍키역",
      "id": 11
    }
  ],
  "lines": [
    {
      "name": "67호선",
      "color": "#10B981",
      "id": 6
    },
    {
      "name": "58호선",
      "color": "#FB923C",
      "id": 7
    },
    {
      "name": "99호선",
      "upStationId": 10,
      "downStationId": 0,
      "distance": 100000,
      "color": "#A78BFA",
      "id": 8
    }
  ]
}